[{"domain":null,"method":"GET|HEAD","uri":"\/","name":null,"action":"Closure","middleware":["web"],"path":"routes\/web.php:7"},{"domain":null,"method":"GET|HEAD","uri":"admin","name":"filament.admin.pages.dashboard","action":"Filament\\Pages\\Dashboard","middleware":["Filament\\Http\\Middleware\\SetUpPanel:admin","Illuminate\\Cookie\\Middleware\\EncryptCookies","Illuminate\\Cookie\\Middleware\\AddQueuedCookiesToResponse","Illuminate\\Session\\Middleware\\StartSession","Illuminate\\View\\Middleware\\ShareErrorsFromSession","Filament\\Http\\Middleware\\Authenticate","Filament\\Http\\Middleware\\AuthenticateSession","Illuminate\\Foundation\\Http\\Middleware\\VerifyCsrfToken","Illuminate\\Routing\\Middleware\\SubstituteBindings","Filament\\Http\\Middleware\\DisableBladeIconComponents","Filament\\Http\\Middleware\\DispatchServingFilamentEvent"],"path":null},{"domain":null,"method":"GET|HEAD","uri":"admin\/ai-routing-page","name":"filament.admin.pages.ai-routing-page","action":"App\\Filament\\Pages\\AiRoutingPage","middleware":["Filament\\Http\\Middleware\\SetUpPanel:admin","Illuminate\\Cookie\\Middleware\\EncryptCookies","Illuminate\\Cookie\\Middleware\\AddQueuedCookiesToResponse","Illuminate\\Session\\Middleware\\StartSession","Illuminate\\View\\Middleware\\ShareErrorsFromSession","Filament\\Http\\Middleware\\Authenticate","Filament\\Http\\Middleware\\AuthenticateSession","Illuminate\\Foundation\\Http\\Middleware\\VerifyCsrfToken","Illuminate\\Routing\\Middleware\\SubstituteBindings","Filament\\Http\\Middleware\\DisableBladeIconComponents","Filament\\Http\\Middleware\\DispatchServingFilamentEvent"],"path":null},{"domain":null,"method":"GET|HEAD","uri":"admin\/audit-logs","name":"filament.admin.resources.audit-logs.index","action":"App\\Filament\\Resources\\AuditLogResource\\Pages\\ListAuditLogs","middleware":["Filament\\Http\\Middleware\\SetUpPanel:admin","Illuminate\\Cookie\\Middleware\\EncryptCookies","Illuminate\\Cookie\\Middleware\\AddQueuedCookiesToResponse","Illuminate\\Session\\Middleware\\StartSession","Illuminate\\View\\Middleware\\ShareErrorsFromSession","Filament\\Http\\Middleware\\Authenticate","Filament\\Http\\Middleware\\AuthenticateSession","Illuminate\\Foundation\\Http\\Middleware\\VerifyCsrfToken","Illuminate\\Routing\\Middleware\\SubstituteBindings","Filament\\Http\\Middleware\\DisableBladeIconComponents","Filament\\Http\\Middleware\\DispatchServingFilamentEvent"],"path":null},{"domain":null,"method":"GET|HEAD","uri":"admin\/audit-logs\/{record}","name":"filament.admin.resources.audit-logs.view","action":"App\\Filament\\Resources\\AuditLogResource\\Pages\\ViewAuditLog","middleware":["Filament\\Http\\Middleware\\SetUpPanel:admin","Illuminate\\Cookie\\Middleware\\EncryptCookies","Illuminate\\Cookie\\Middleware\\AddQueuedCookiesToResponse","Illuminate\\Session\\Middleware\\StartSession","Illuminate\\View\\Middleware\\ShareErrorsFromSession","Filament\\Http\\Middleware\\Authenticate","Filament\\Http\\Middleware\\AuthenticateSession","Illuminate\\Foundation\\Http\\Middleware\\VerifyCsrfToken","Illuminate\\Routing\\Middleware\\SubstituteBindings","Filament\\Http\\Middleware\\DisableBladeIconComponents","Filament\\Http\\Middleware\\DispatchServingFilamentEvent"],"path":null},{"domain":null,"method":"GET|HEAD","uri":"admin\/exam-bodies","name":"filament.admin.resources.exam-bodies.index","action":"App\\Filament\\Resources\\ExamBodyResource\\Pages\\ListExamBodies","middleware":["Filament\\Http\\Middleware\\SetUpPanel:admin","Illuminate\\Cookie\\Middleware\\EncryptCookies","Illuminate\\Cookie\\Middleware\\AddQueuedCookiesToResponse","Illuminate\\Session\\Middleware\\StartSession","Illuminate\\View\\Middleware\\ShareErrorsFromSession","Filament\\Http\\Middleware\\Authenticate","Filament\\Http\\Middleware\\AuthenticateSession","Illuminate\\Foundation\\Http\\Middleware\\VerifyCsrfToken","Illuminate\\Routing\\Middleware\\SubstituteBindings","Filament\\Http\\Middleware\\DisableBladeIconComponents","Filament\\Http\\Middleware\\DispatchServingFilamentEvent"],"path":null},{"domain":null,"method":"GET|HEAD","uri":"admin\/exam-bodies\/create","name":"filament.admin.resources.exam-bodies.create","action":"App\\Filament\\Resources\\ExamBodyResource\\Pages\\CreateExamBody","middleware":["Filament\\Http\\Middleware\\SetUpPanel:admin","Illuminate\\Cookie\\Middleware\\EncryptCookies","Illuminate\\Cookie\\Middleware\\AddQueuedCookiesToResponse","Illuminate\\Session\\Middleware\\StartSession","Illuminate\\View\\Middleware\\ShareErrorsFromSession","Filament\\Http\\Middleware\\Authenticate","Filament\\Http\\Middleware\\AuthenticateSession","Illuminate\\Foundation\\Http\\Middleware\\VerifyCsrfToken","Illuminate\\Routing\\Middleware\\SubstituteBindings","Filament\\Http\\Middleware\\DisableBladeIconComponents","Filament\\Http\\Middleware\\DispatchServingFilamentEvent"],"path":null},{"domain":null,"method":"GET|HEAD","uri":"admin\/exam-bodies\/{record}","name":"filament.admin.resources.exam-bodies.view","action":"App\\Filament\\Resources\\ExamBodyResource\\Pages\\ViewExamBody","middleware":["Filament\\Http\\Middleware\\SetUpPanel:admin","Illuminate\\Cookie\\Middleware\\EncryptCookies","Illuminate\\Cookie\\Middleware\\AddQueuedCookiesToResponse","Illuminate\\Session\\Middleware\\StartSession","Illuminate\\View\\Middleware\\ShareErrorsFromSession","Filament\\Http\\Middleware\\Authenticate","Filament\\Http\\Middleware\\AuthenticateSession","Illuminate\\Foundation\\Http\\Middleware\\VerifyCsrfToken","Illuminate\\Routing\\Middleware\\SubstituteBindings","Filament\\Http\\Middleware\\DisableBladeIconComponents","Filament\\Http\\Middleware\\DispatchServingFilamentEvent"],"path":null},{"domain":null,"method":"GET|HEAD","uri":"admin\/exam-bodies\/{record}\/edit","name":"filament.admin.resources.exam-bodies.edit","action":"App\\Filament\\Resources\\ExamBodyResource\\Pages\\EditExamBody","middleware":["Filament\\Http\\Middleware\\SetUpPanel:admin","Illuminate\\Cookie\\Middleware\\EncryptCookies","Illuminate\\Cookie\\Middleware\\AddQueuedCookiesToResponse","Illuminate\\Session\\Middleware\\StartSession","Illuminate\\View\\Middleware\\ShareErrorsFromSession","Filament\\Http\\Middleware\\Authenticate","Filament\\Http\\Middleware\\AuthenticateSession","Illuminate\\Foundation\\Http\\Middleware\\VerifyCsrfToken","Illuminate\\Routing\\Middleware\\SubstituteBindings","Filament\\Http\\Middleware\\DisableBladeIconComponents","Filament\\Http\\Middleware\\DispatchServingFilamentEvent"],"path":null},{"domain":null,"method":"GET|HEAD","uri":"admin\/exam-papers","name":"filament.admin.resources.exam-papers.index","action":"App\\Filament\\Resources\\ExamPapersResource\\Pages\\ListExamPapers","middleware":["Filament\\Http\\Middleware\\SetUpPanel:admin","Illuminate\\Cookie\\Middleware\\EncryptCookies","Illuminate\\Cookie\\Middleware\\AddQueuedCookiesToResponse","Illuminate\\Session\\Middleware\\StartSession","Illuminate\\View\\Middleware\\ShareErrorsFromSession","Filament\\Http\\Middleware\\Authenticate","Filament\\Http\\Middleware\\AuthenticateSession","Illuminate\\Foundation\\Http\\Middleware\\VerifyCsrfToken","Illuminate\\Routing\\Middleware\\SubstituteBindings","Filament\\Http\\Middleware\\DisableBladeIconComponents","Filament\\Http\\Middleware\\DispatchServingFilamentEvent"],"path":null},{"domain":null,"method":"GET|HEAD","uri":"admin\/exam-papers\/create","name":"filament.admin.resources.exam-papers.create","action":"App\\Filament\\Resources\\ExamPapersResource\\Pages\\CreateExamPaper","middleware":["Filament\\Http\\Middleware\\SetUpPanel:admin","Illuminate\\Cookie\\Middleware\\EncryptCookies","Illuminate\\Cookie\\Middleware\\AddQueuedCookiesToResponse","Illuminate\\Session\\Middleware\\StartSession","Illuminate\\View\\Middleware\\ShareErrorsFromSession","Filament\\Http\\Middleware\\Authenticate","Filament\\Http\\Middleware\\AuthenticateSession","Illuminate\\Foundation\\Http\\Middleware\\VerifyCsrfToken","Illuminate\\Routing\\Middleware\\SubstituteBindings","Filament\\Http\\Middleware\\DisableBladeIconComponents","Filament\\Http\\Middleware\\DispatchServingFilamentEvent"],"path":null},{"domain":null,"method":"GET|HEAD","uri":"admin\/exam-papers\/{record}","name":"filament.admin.resources.exam-papers.view","action":"App\\Filament\\Resources\\ExamPapersResource\\Pages\\ViewExamPaper","middleware":["Filament\\Http\\Middleware\\SetUpPanel:admin","Illuminate\\Cookie\\Middleware\\EncryptCookies","Illuminate\\Cookie\\Middleware\\AddQueuedCookiesToResponse","Illuminate\\Session\\Middleware\\StartSession","Illuminate\\View\\Middleware\\ShareErrorsFromSession","Filament\\Http\\Middleware\\Authenticate","Filament\\Http\\Middleware\\AuthenticateSession","Illuminate\\Foundation\\Http\\Middleware\\VerifyCsrfToken","Illuminate\\Routing\\Middleware\\SubstituteBindings","Filament\\Http\\Middleware\\DisableBladeIconComponents","Filament\\Http\\Middleware\\DispatchServingFilamentEvent"],"path":null},{"domain":null,"method":"GET|HEAD","uri":"admin\/exam-papers\/{record}\/edit","name":"filament.admin.resources.exam-papers.edit","action":"App\\Filament\\Resources\\ExamPapersResource\\Pages\\EditExamPaper","middleware":["Filament\\Http\\Middleware\\SetUpPanel:admin","Illuminate\\Cookie\\Middleware\\EncryptCookies","Illuminate\\Cookie\\Middleware\\AddQueuedCookiesToResponse","Illuminate\\Session\\Middleware\\StartSession","Illuminate\\View\\Middleware\\ShareErrorsFromSession","Filament\\Http\\Middleware\\Authenticate","Filament\\Http\\Middleware\\AuthenticateSession","Illuminate\\Foundation\\Http\\Middleware\\VerifyCsrfToken","Illuminate\\Routing\\Middleware\\SubstituteBindings","Filament\\Http\\Middleware\\DisableBladeIconComponents","Filament\\Http\\Middleware\\DispatchServingFilamentEvent"],"path":null},{"domain":null,"method":"GET|HEAD","uri":"admin\/exam-subjects","name":"filament.admin.resources.exam-subjects.index","action":"App\\Filament\\Resources\\ExamSubjectResource\\Pages\\ListExamSubjects","middleware":["Filament\\Http\\Middleware\\SetUpPanel:admin","Illuminate\\Cookie\\Middleware\\EncryptCookies","Illuminate\\Cookie\\Middleware\\AddQueuedCookiesToResponse","Illuminate\\Session\\Middleware\\StartSession","Illuminate\\View\\Middleware\\ShareErrorsFromSession","Filament\\Http\\Middleware\\Authenticate","Filament\\Http\\Middleware\\AuthenticateSession","Illuminate\\Foundation\\Http\\Middleware\\VerifyCsrfToken","Illuminate\\Routing\\Middleware\\SubstituteBindings","Filament\\Http\\Middleware\\DisableBladeIconComponents","Filament\\Http\\Middleware\\DispatchServingFilamentEvent"],"path":null},{"domain":null,"method":"GET|HEAD","uri":"admin\/exam-subjects\/create","name":"filament.admin.resources.exam-subjects.create","action":"App\\Filament\\Resources\\ExamSubjectResource\\Pages\\CreateExamSubject","middleware":["Filament\\Http\\Middleware\\SetUpPanel:admin","Illuminate\\Cookie\\Middleware\\EncryptCookies","Illuminate\\Cookie\\Middleware\\AddQueuedCookiesToResponse","Illuminate\\Session\\Middleware\\StartSession","Illuminate\\View\\Middleware\\ShareErrorsFromSession","Filament\\Http\\Middleware\\Authenticate","Filament\\Http\\Middleware\\AuthenticateSession","Illuminate\\Foundation\\Http\\Middleware\\VerifyCsrfToken","Illuminate\\Routing\\Middleware\\SubstituteBindings","Filament\\Http\\Middleware\\DisableBladeIconComponents","Filament\\Http\\Middleware\\DispatchServingFilamentEvent"],"path":null},{"domain":null,"method":"GET|HEAD","uri":"admin\/exam-subjects\/{record}","name":"filament.admin.resources.exam-subjects.view","action":"App\\Filament\\Resources\\ExamSubjectResource\\Pages\\ViewExamSubject","middleware":["Filament\\Http\\Middleware\\SetUpPanel:admin","Illuminate\\Cookie\\Middleware\\EncryptCookies","Illuminate\\Cookie\\Middleware\\AddQueuedCookiesToResponse","Illuminate\\Session\\Middleware\\StartSession","Illuminate\\View\\Middleware\\ShareErrorsFromSession","Filament\\Http\\Middleware\\Authenticate","Filament\\Http\\Middleware\\AuthenticateSession","Illuminate\\Foundation\\Http\\Middleware\\VerifyCsrfToken","Illuminate\\Routing\\Middleware\\SubstituteBindings","Filament\\Http\\Middleware\\DisableBladeIconComponents","Filament\\Http\\Middleware\\DispatchServingFilamentEvent"],"path":null},{"domain":null,"method":"GET|HEAD","uri":"admin\/exam-subjects\/{record}\/edit","name":"filament.admin.resources.exam-subjects.edit","action":"App\\Filament\\Resources\\ExamSubjectResource\\Pages\\EditExamSubject","middleware":["Filament\\Http\\Middleware\\SetUpPanel:admin","Illuminate\\Cookie\\Middleware\\EncryptCookies","Illuminate\\Cookie\\Middleware\\AddQueuedCookiesToResponse","Illuminate\\Session\\Middleware\\StartSession","Illuminate\\View\\Middleware\\ShareErrorsFromSession","Filament\\Http\\Middleware\\Authenticate","Filament\\Http\\Middleware\\AuthenticateSession","Illuminate\\Foundation\\Http\\Middleware\\VerifyCsrfToken","Illuminate\\Routing\\Middleware\\SubstituteBindings","Filament\\Http\\Middleware\\DisableBladeIconComponents","Filament\\Http\\Middleware\\DispatchServingFilamentEvent"],"path":null},{"domain":null,"method":"GET|HEAD","uri":"admin\/ingestion-jobs","name":"filament.admin.resources.ingestion-jobs.index","action":"App\\Filament\\Resources\\IngestionJobsResource\\Pages\\ListIngestionJobs","middleware":["Filament\\Http\\Middleware\\SetUpPanel:admin","Illuminate\\Cookie\\Middleware\\EncryptCookies","Illuminate\\Cookie\\Middleware\\AddQueuedCookiesToResponse","Illuminate\\Session\\Middleware\\StartSession","Illuminate\\View\\Middleware\\ShareErrorsFromSession","Filament\\Http\\Middleware\\Authenticate","Filament\\Http\\Middleware\\AuthenticateSession","Illuminate\\Foundation\\Http\\Middleware\\VerifyCsrfToken","Illuminate\\Routing\\Middleware\\SubstituteBindings","Filament\\Http\\Middleware\\DisableBladeIconComponents","Filament\\Http\\Middleware\\DispatchServingFilamentEvent"],"path":null},{"domain":null,"method":"GET|HEAD","uri":"admin\/ingestion-jobs\/{record}","name":"filament.admin.resources.ingestion-jobs.view","action":"App\\Filament\\Resources\\IngestionJobsResource\\Pages\\ViewIngestionJob","middleware":["Filament\\Http\\Middleware\\SetUpPanel:admin","Illuminate\\Cookie\\Middleware\\EncryptCookies","Illuminate\\Cookie\\Middleware\\AddQueuedCookiesToResponse","Illuminate\\Session\\Middleware\\StartSession","Illuminate\\View\\Middleware\\ShareErrorsFromSession","Filament\\Http\\Middleware\\Authenticate","Filament\\Http\\Middleware\\AuthenticateSession","Illuminate\\Foundation\\Http\\Middleware\\VerifyCsrfToken","Illuminate\\Routing\\Middleware\\SubstituteBindings","Filament\\Http\\Middleware\\DisableBladeIconComponents","Filament\\Http\\Middleware\\DispatchServingFilamentEvent"],"path":null},{"domain":null,"method":"GET|HEAD","uri":"admin\/login","name":"filament.admin.auth.login","action":"Filament\\Pages\\Auth\\Login","middleware":["Filament\\Http\\Middleware\\SetUpPanel:admin","Illuminate\\Cookie\\Middleware\\EncryptCookies","Illuminate\\Cookie\\Middleware\\AddQueuedCookiesToResponse","Illuminate\\Session\\Middleware\\StartSession","Illuminate\\View\\Middleware\\ShareErrorsFromSession","Filament\\Http\\Middleware\\AuthenticateSession","Illuminate\\Foundation\\Http\\Middleware\\VerifyCsrfToken","Illuminate\\Routing\\Middleware\\SubstituteBindings","Filament\\Http\\Middleware\\DisableBladeIconComponents","Filament\\Http\\Middleware\\DispatchServingFilamentEvent"],"path":null},{"domain":null,"method":"POST","uri":"admin\/logout","name":"filament.admin.auth.logout","action":"Filament\\Http\\Controllers\\Auth\\LogoutController","middleware":["Filament\\Http\\Middleware\\SetUpPanel:admin","Illuminate\\Cookie\\Middleware\\EncryptCookies","Illuminate\\Cookie\\Middleware\\AddQueuedCookiesToResponse","Illuminate\\Session\\Middleware\\StartSession","Illuminate\\View\\Middleware\\ShareErrorsFromSession","Filament\\Http\\Middleware\\Authenticate","Filament\\Http\\Middleware\\AuthenticateSession","Illuminate\\Foundation\\Http\\Middleware\\VerifyCsrfToken","Illuminate\\Routing\\Middleware\\SubstituteBindings","Filament\\Http\\Middleware\\DisableBladeIconComponents","Filament\\Http\\Middleware\\DispatchServingFilamentEvent"],"path":null},{"domain":null,"method":"GET|HEAD","uri":"admin\/question-drafts","name":"filament.admin.resources.question-drafts.index","action":"App\\Filament\\Resources\\QuestionDraftsResource\\Pages\\ListQuestionDrafts","middleware":["Filament\\Http\\Middleware\\SetUpPanel:admin","Illuminate\\Cookie\\Middleware\\EncryptCookies","Illuminate\\Cookie\\Middleware\\AddQueuedCookiesToResponse","Illuminate\\Session\\Middleware\\StartSession","Illuminate\\View\\Middleware\\ShareErrorsFromSession","Filament\\Http\\Middleware\\Authenticate","Filament\\Http\\Middleware\\AuthenticateSession","Illuminate\\Foundation\\Http\\Middleware\\VerifyCsrfToken","Illuminate\\Routing\\Middleware\\SubstituteBindings","Filament\\Http\\Middleware\\DisableBladeIconComponents","Filament\\Http\\Middleware\\DispatchServingFilamentEvent"],"path":null},{"domain":null,"method":"GET|HEAD","uri":"admin\/question-drafts\/{record}","name":"filament.admin.resources.question-drafts.view","action":"App\\Filament\\Resources\\QuestionDraftsResource\\Pages\\ViewQuestionDraft","middleware":["Filament\\Http\\Middleware\\SetUpPanel:admin","Illuminate\\Cookie\\Middleware\\EncryptCookies","Illuminate\\Cookie\\Middleware\\AddQueuedCookiesToResponse","Illuminate\\Session\\Middleware\\StartSession","Illuminate\\View\\Middleware\\ShareErrorsFromSession","Filament\\Http\\Middleware\\Authenticate","Filament\\Http\\Middleware\\AuthenticateSession","Illuminate\\Foundation\\Http\\Middleware\\VerifyCsrfToken","Illuminate\\Routing\\Middleware\\SubstituteBindings","Filament\\Http\\Middleware\\DisableBladeIconComponents","Filament\\Http\\Middleware\\DispatchServingFilamentEvent"],"path":null},{"domain":null,"method":"GET|HEAD","uri":"admin\/question-drafts\/{record}\/edit","name":"filament.admin.resources.question-drafts.edit","action":"App\\Filament\\Resources\\QuestionDraftsResource\\Pages\\EditQuestionDraft","middleware":["Filament\\Http\\Middleware\\SetUpPanel:admin","Illuminate\\Cookie\\Middleware\\EncryptCookies","Illuminate\\Cookie\\Middleware\\AddQueuedCookiesToResponse","Illuminate\\Session\\Middleware\\StartSession","Illuminate\\View\\Middleware\\ShareErrorsFromSession","Filament\\Http\\Middleware\\Authenticate","Filament\\Http\\Middleware\\AuthenticateSession","Illuminate\\Foundation\\Http\\Middleware\\VerifyCsrfToken","Illuminate\\Routing\\Middleware\\SubstituteBindings","Filament\\Http\\Middleware\\DisableBladeIconComponents","Filament\\Http\\Middleware\\DispatchServingFilamentEvent"],"path":null},{"domain":null,"method":"GET|HEAD","uri":"admin\/question-reports","name":"filament.admin.resources.question-reports.index","action":"App\\Filament\\Resources\\QuestionReportsResource\\Pages\\ListQuestionReports","middleware":["Filament\\Http\\Middleware\\SetUpPanel:admin","Illuminate\\Cookie\\Middleware\\EncryptCookies","Illuminate\\Cookie\\Middleware\\AddQueuedCookiesToResponse","Illuminate\\Session\\Middleware\\StartSession","Illuminate\\View\\Middleware\\ShareErrorsFromSession","Filament\\Http\\Middleware\\Authenticate","Filament\\Http\\Middleware\\AuthenticateSession","Illuminate\\Foundation\\Http\\Middleware\\VerifyCsrfToken","Illuminate\\Routing\\Middleware\\SubstituteBindings","Filament\\Http\\Middleware\\DisableBladeIconComponents","Filament\\Http\\Middleware\\DispatchServingFilamentEvent"],"path":null},{"domain":null,"method":"GET|HEAD","uri":"admin\/question-reports\/{record}","name":"filament.admin.resources.question-reports.view","action":"App\\Filament\\Resources\\QuestionReportsResource\\Pages\\ViewQuestionReport","middleware":["Filament\\Http\\Middleware\\SetUpPanel:admin","Illuminate\\Cookie\\Middleware\\EncryptCookies","Illuminate\\Cookie\\Middleware\\AddQueuedCookiesToResponse","Illuminate\\Session\\Middleware\\StartSession","Illuminate\\View\\Middleware\\ShareErrorsFromSession","Filament\\Http\\Middleware\\Authenticate","Filament\\Http\\Middleware\\AuthenticateSession","Illuminate\\Foundation\\Http\\Middleware\\VerifyCsrfToken","Illuminate\\Routing\\Middleware\\SubstituteBindings","Filament\\Http\\Middleware\\DisableBladeIconComponents","Filament\\Http\\Middleware\\DispatchServingFilamentEvent"],"path":null},{"domain":null,"method":"GET|HEAD","uri":"admin\/question-reports\/{record}\/edit","name":"filament.admin.resources.question-reports.edit","action":"App\\Filament\\Resources\\QuestionReportsResource\\Pages\\EditQuestionReport","middleware":["Filament\\Http\\Middleware\\SetUpPanel:admin","Illuminate\\Cookie\\Middleware\\EncryptCookies","Illuminate\\Cookie\\Middleware\\AddQueuedCookiesToResponse","Illuminate\\Session\\Middleware\\StartSession","Illuminate\\View\\Middleware\\ShareErrorsFromSession","Filament\\Http\\Middleware\\Authenticate","Filament\\Http\\Middleware\\AuthenticateSession","Illuminate\\Foundation\\Http\\Middleware\\VerifyCsrfToken","Illuminate\\Routing\\Middleware\\SubstituteBindings","Filament\\Http\\Middleware\\DisableBladeIconComponents","Filament\\Http\\Middleware\\DispatchServingFilamentEvent"],"path":null},{"domain":null,"method":"GET|HEAD","uri":"admin\/questions","name":"filament.admin.resources.questions.index","action":"App\\Filament\\Resources\\QuestionsResource\\Pages\\ListQuestions","middleware":["Filament\\Http\\Middleware\\SetUpPanel:admin","Illuminate\\Cookie\\Middleware\\EncryptCookies","Illuminate\\Cookie\\Middleware\\AddQueuedCookiesToResponse","Illuminate\\Session\\Middleware\\StartSession","Illuminate\\View\\Middleware\\ShareErrorsFromSession","Filament\\Http\\Middleware\\Authenticate","Filament\\Http\\Middleware\\AuthenticateSession","Illuminate\\Foundation\\Http\\Middleware\\VerifyCsrfToken","Illuminate\\Routing\\Middleware\\SubstituteBindings","Filament\\Http\\Middleware\\DisableBladeIconComponents","Filament\\Http\\Middleware\\DispatchServingFilamentEvent"],"path":null},{"domain":null,"method":"GET|HEAD","uri":"admin\/questions\/create","name":"filament.admin.resources.questions.create","action":"App\\Filament\\Resources\\QuestionsResource\\Pages\\CreateQuestion","middleware":["Filament\\Http\\Middleware\\SetUpPanel:admin","Illuminate\\Cookie\\Middleware\\EncryptCookies","Illuminate\\Cookie\\Middleware\\AddQueuedCookiesToResponse","Illuminate\\Session\\Middleware\\StartSession","Illuminate\\View\\Middleware\\ShareErrorsFromSession","Filament\\Http\\Middleware\\Authenticate","Filament\\Http\\Middleware\\AuthenticateSession","Illuminate\\Foundation\\Http\\Middleware\\VerifyCsrfToken","Illuminate\\Routing\\Middleware\\SubstituteBindings","Filament\\Http\\Middleware\\DisableBladeIconComponents","Filament\\Http\\Middleware\\DispatchServingFilamentEvent"],"path":null},{"domain":null,"method":"GET|HEAD","uri":"admin\/questions\/{record}","name":"filament.admin.resources.questions.view","action":"App\\Filament\\Resources\\QuestionsResource\\Pages\\ViewQuestion","middleware":["Filament\\Http\\Middleware\\SetUpPanel:admin","Illuminate\\Cookie\\Middleware\\EncryptCookies","Illuminate\\Cookie\\Middleware\\AddQueuedCookiesToResponse","Illuminate\\Session\\Middleware\\StartSession","Illuminate\\View\\Middleware\\ShareErrorsFromSession","Filament\\Http\\Middleware\\Authenticate","Filament\\Http\\Middleware\\AuthenticateSession","Illuminate\\Foundation\\Http\\Middleware\\VerifyCsrfToken","Illuminate\\Routing\\Middleware\\SubstituteBindings","Filament\\Http\\Middleware\\DisableBladeIconComponents","Filament\\Http\\Middleware\\DispatchServingFilamentEvent"],"path":null},{"domain":null,"method":"GET|HEAD","uri":"admin\/questions\/{record}\/edit","name":"filament.admin.resources.questions.edit","action":"App\\Filament\\Resources\\QuestionsResource\\Pages\\EditQuestion","middleware":["Filament\\Http\\Middleware\\SetUpPanel:admin","Illuminate\\Cookie\\Middleware\\EncryptCookies","Illuminate\\Cookie\\Middleware\\AddQueuedCookiesToResponse","Illuminate\\Session\\Middleware\\StartSession","Illuminate\\View\\Middleware\\ShareErrorsFromSession","Filament\\Http\\Middleware\\Authenticate","Filament\\Http\\Middleware\\AuthenticateSession","Illuminate\\Foundation\\Http\\Middleware\\VerifyCsrfToken","Illuminate\\Routing\\Middleware\\SubstituteBindings","Filament\\Http\\Middleware\\DisableBladeIconComponents","Filament\\Http\\Middleware\\DispatchServingFilamentEvent"],"path":null},{"domain":null,"method":"GET|HEAD","uri":"admin\/review-workbench-page","name":"filament.admin.pages.review-workbench-page","action":"App\\Filament\\Pages\\ReviewWorkbenchPage","middleware":["Filament\\Http\\Middleware\\SetUpPanel:admin","Illuminate\\Cookie\\Middleware\\EncryptCookies","Illuminate\\Cookie\\Middleware\\AddQueuedCookiesToResponse","Illuminate\\Session\\Middleware\\StartSession","Illuminate\\View\\Middleware\\ShareErrorsFromSession","Filament\\Http\\Middleware\\Authenticate","Filament\\Http\\Middleware\\AuthenticateSession","Illuminate\\Foundation\\Http\\Middleware\\VerifyCsrfToken","Illuminate\\Routing\\Middleware\\SubstituteBindings","Filament\\Http\\Middleware\\DisableBladeIconComponents","Filament\\Http\\Middleware\\DispatchServingFilamentEvent"],"path":null},{"domain":null,"method":"GET|HEAD","uri":"admin\/roles","name":"filament.admin.resources.roles.index","action":"App\\Filament\\Resources\\RoleResource\\Pages\\ListRoles","middleware":["Filament\\Http\\Middleware\\SetUpPanel:admin","Illuminate\\Cookie\\Middleware\\EncryptCookies","Illuminate\\Cookie\\Middleware\\AddQueuedCookiesToResponse","Illuminate\\Session\\Middleware\\StartSession","Illuminate\\View\\Middleware\\ShareErrorsFromSession","Filament\\Http\\Middleware\\Authenticate","Filament\\Http\\Middleware\\AuthenticateSession","Illuminate\\Foundation\\Http\\Middleware\\VerifyCsrfToken","Illuminate\\Routing\\Middleware\\SubstituteBindings","Filament\\Http\\Middleware\\DisableBladeIconComponents","Filament\\Http\\Middleware\\DispatchServingFilamentEvent"],"path":null},{"domain":null,"method":"GET|HEAD","uri":"admin\/roles\/create","name":"filament.admin.resources.roles.create","action":"App\\Filament\\Resources\\RoleResource\\Pages\\CreateRole","middleware":["Filament\\Http\\Middleware\\SetUpPanel:admin","Illuminate\\Cookie\\Middleware\\EncryptCookies","Illuminate\\Cookie\\Middleware\\AddQueuedCookiesToResponse","Illuminate\\Session\\Middleware\\StartSession","Illuminate\\View\\Middleware\\ShareErrorsFromSession","Filament\\Http\\Middleware\\Authenticate","Filament\\Http\\Middleware\\AuthenticateSession","Illuminate\\Foundation\\Http\\Middleware\\VerifyCsrfToken","Illuminate\\Routing\\Middleware\\SubstituteBindings","Filament\\Http\\Middleware\\DisableBladeIconComponents","Filament\\Http\\Middleware\\DispatchServingFilamentEvent"],"path":null},{"domain":null,"method":"GET|HEAD","uri":"admin\/roles\/{record}\/edit","name":"filament.admin.resources.roles.edit","action":"App\\Filament\\Resources\\RoleResource\\Pages\\EditRole","middleware":["Filament\\Http\\Middleware\\SetUpPanel:admin","Illuminate\\Cookie\\Middleware\\EncryptCookies","Illuminate\\Cookie\\Middleware\\AddQueuedCookiesToResponse","Illuminate\\Session\\Middleware\\StartSession","Illuminate\\View\\Middleware\\ShareErrorsFromSession","Filament\\Http\\Middleware\\Authenticate","Filament\\Http\\Middleware\\AuthenticateSession","Illuminate\\Foundation\\Http\\Middleware\\VerifyCsrfToken","Illuminate\\Routing\\Middleware\\SubstituteBindings","Filament\\Http\\Middleware\\DisableBladeIconComponents","Filament\\Http\\Middleware\\DispatchServingFilamentEvent"],"path":null},{"domain":null,"method":"GET|HEAD","uri":"admin\/subjects","name":"filament.admin.resources.subjects.index","action":"App\\Filament\\Resources\\SubjectResource\\Pages\\ListSubjects","middleware":["Filament\\Http\\Middleware\\SetUpPanel:admin","Illuminate\\Cookie\\Middleware\\EncryptCookies","Illuminate\\Cookie\\Middleware\\AddQueuedCookiesToResponse","Illuminate\\Session\\Middleware\\StartSession","Illuminate\\View\\Middleware\\ShareErrorsFromSession","Filament\\Http\\Middleware\\Authenticate","Filament\\Http\\Middleware\\AuthenticateSession","Illuminate\\Foundation\\Http\\Middleware\\VerifyCsrfToken","Illuminate\\Routing\\Middleware\\SubstituteBindings","Filament\\Http\\Middleware\\DisableBladeIconComponents","Filament\\Http\\Middleware\\DispatchServingFilamentEvent"],"path":null},{"domain":null,"method":"GET|HEAD","uri":"admin\/subjects\/create","name":"filament.admin.resources.subjects.create","action":"App\\Filament\\Resources\\SubjectResource\\Pages\\CreateSubject","middleware":["Filament\\Http\\Middleware\\SetUpPanel:admin","Illuminate\\Cookie\\Middleware\\EncryptCookies","Illuminate\\Cookie\\Middleware\\AddQueuedCookiesToResponse","Illuminate\\Session\\Middleware\\StartSession","Illuminate\\View\\Middleware\\ShareErrorsFromSession","Filament\\Http\\Middleware\\Authenticate","Filament\\Http\\Middleware\\AuthenticateSession","Illuminate\\Foundation\\Http\\Middleware\\VerifyCsrfToken","Illuminate\\Routing\\Middleware\\SubstituteBindings","Filament\\Http\\Middleware\\DisableBladeIconComponents","Filament\\Http\\Middleware\\DispatchServingFilamentEvent"],"path":null},{"domain":null,"method":"GET|HEAD","uri":"admin\/subjects\/{record}","name":"filament.admin.resources.subjects.view","action":"App\\Filament\\Resources\\SubjectResource\\Pages\\ViewSubject","middleware":["Filament\\Http\\Middleware\\SetUpPanel:admin","Illuminate\\Cookie\\Middleware\\EncryptCookies","Illuminate\\Cookie\\Middleware\\AddQueuedCookiesToResponse","Illuminate\\Session\\Middleware\\StartSession","Illuminate\\View\\Middleware\\ShareErrorsFromSession","Filament\\Http\\Middleware\\Authenticate","Filament\\Http\\Middleware\\AuthenticateSession","Illuminate\\Foundation\\Http\\Middleware\\VerifyCsrfToken","Illuminate\\Routing\\Middleware\\SubstituteBindings","Filament\\Http\\Middleware\\DisableBladeIconComponents","Filament\\Http\\Middleware\\DispatchServingFilamentEvent"],"path":null},{"domain":null,"method":"GET|HEAD","uri":"admin\/subjects\/{record}\/edit","name":"filament.admin.resources.subjects.edit","action":"App\\Filament\\Resources\\SubjectResource\\Pages\\EditSubject","middleware":["Filament\\Http\\Middleware\\SetUpPanel:admin","Illuminate\\Cookie\\Middleware\\EncryptCookies","Illuminate\\Cookie\\Middleware\\AddQueuedCookiesToResponse","Illuminate\\Session\\Middleware\\StartSession","Illuminate\\View\\Middleware\\ShareErrorsFromSession","Filament\\Http\\Middleware\\Authenticate","Filament\\Http\\Middleware\\AuthenticateSession","Illuminate\\Foundation\\Http\\Middleware\\VerifyCsrfToken","Illuminate\\Routing\\Middleware\\SubstituteBindings","Filament\\Http\\Middleware\\DisableBladeIconComponents","Filament\\Http\\Middleware\\DispatchServingFilamentEvent"],"path":null},{"domain":null,"method":"GET|HEAD","uri":"admin\/topics","name":"filament.admin.resources.topics.index","action":"App\\Filament\\Resources\\TopicResource\\Pages\\ListTopics","middleware":["Filament\\Http\\Middleware\\SetUpPanel:admin","Illuminate\\Cookie\\Middleware\\EncryptCookies","Illuminate\\Cookie\\Middleware\\AddQueuedCookiesToResponse","Illuminate\\Session\\Middleware\\StartSession","Illuminate\\View\\Middleware\\ShareErrorsFromSession","Filament\\Http\\Middleware\\Authenticate","Filament\\Http\\Middleware\\AuthenticateSession","Illuminate\\Foundation\\Http\\Middleware\\VerifyCsrfToken","Illuminate\\Routing\\Middleware\\SubstituteBindings","Filament\\Http\\Middleware\\DisableBladeIconComponents","Filament\\Http\\Middleware\\DispatchServingFilamentEvent"],"path":null},{"domain":null,"method":"GET|HEAD","uri":"admin\/topics\/create","name":"filament.admin.resources.topics.create","action":"App\\Filament\\Resources\\TopicResource\\Pages\\CreateTopic","middleware":["Filament\\Http\\Middleware\\SetUpPanel:admin","Illuminate\\Cookie\\Middleware\\EncryptCookies","Illuminate\\Cookie\\Middleware\\AddQueuedCookiesToResponse","Illuminate\\Session\\Middleware\\StartSession","Illuminate\\View\\Middleware\\ShareErrorsFromSession","Filament\\Http\\Middleware\\Authenticate","Filament\\Http\\Middleware\\AuthenticateSession","Illuminate\\Foundation\\Http\\Middleware\\VerifyCsrfToken","Illuminate\\Routing\\Middleware\\SubstituteBindings","Filament\\Http\\Middleware\\DisableBladeIconComponents","Filament\\Http\\Middleware\\DispatchServingFilamentEvent"],"path":null},{"domain":null,"method":"GET|HEAD","uri":"admin\/topics\/{record}","name":"filament.admin.resources.topics.view","action":"App\\Filament\\Resources\\TopicResource\\Pages\\ViewTopic","middleware":["Filament\\Http\\Middleware\\SetUpPanel:admin","Illuminate\\Cookie\\Middleware\\EncryptCookies","Illuminate\\Cookie\\Middleware\\AddQueuedCookiesToResponse","Illuminate\\Session\\Middleware\\StartSession","Illuminate\\View\\Middleware\\ShareErrorsFromSession","Filament\\Http\\Middleware\\Authenticate","Filament\\Http\\Middleware\\AuthenticateSession","Illuminate\\Foundation\\Http\\Middleware\\VerifyCsrfToken","Illuminate\\Routing\\Middleware\\SubstituteBindings","Filament\\Http\\Middleware\\DisableBladeIconComponents","Filament\\Http\\Middleware\\DispatchServingFilamentEvent"],"path":null},{"domain":null,"method":"GET|HEAD","uri":"admin\/topics\/{record}\/edit","name":"filament.admin.resources.topics.edit","action":"App\\Filament\\Resources\\TopicResource\\Pages\\EditTopic","middleware":["Filament\\Http\\Middleware\\SetUpPanel:admin","Illuminate\\Cookie\\Middleware\\EncryptCookies","Illuminate\\Cookie\\Middleware\\AddQueuedCookiesToResponse","Illuminate\\Session\\Middleware\\StartSession","Illuminate\\View\\Middleware\\ShareErrorsFromSession","Filament\\Http\\Middleware\\Authenticate","Filament\\Http\\Middleware\\AuthenticateSession","Illuminate\\Foundation\\Http\\Middleware\\VerifyCsrfToken","Illuminate\\Routing\\Middleware\\SubstituteBindings","Filament\\Http\\Middleware\\DisableBladeIconComponents","Filament\\Http\\Middleware\\DispatchServingFilamentEvent"],"path":null},{"domain":null,"method":"GET|HEAD","uri":"admin\/users","name":"filament.admin.resources.users.index","action":"App\\Filament\\Resources\\UserResource\\Pages\\ListUsers","middleware":["Filament\\Http\\Middleware\\SetUpPanel:admin","Illuminate\\Cookie\\Middleware\\EncryptCookies","Illuminate\\Cookie\\Middleware\\AddQueuedCookiesToResponse","Illuminate\\Session\\Middleware\\StartSession","Illuminate\\View\\Middleware\\ShareErrorsFromSession","Filament\\Http\\Middleware\\Authenticate","Filament\\Http\\Middleware\\AuthenticateSession","Illuminate\\Foundation\\Http\\Middleware\\VerifyCsrfToken","Illuminate\\Routing\\Middleware\\SubstituteBindings","Filament\\Http\\Middleware\\DisableBladeIconComponents","Filament\\Http\\Middleware\\DispatchServingFilamentEvent"],"path":null},{"domain":null,"method":"GET|HEAD","uri":"admin\/users\/create","name":"filament.admin.resources.users.create","action":"App\\Filament\\Resources\\UserResource\\Pages\\CreateUser","middleware":["Filament\\Http\\Middleware\\SetUpPanel:admin","Illuminate\\Cookie\\Middleware\\EncryptCookies","Illuminate\\Cookie\\Middleware\\AddQueuedCookiesToResponse","Illuminate\\Session\\Middleware\\StartSession","Illuminate\\View\\Middleware\\ShareErrorsFromSession","Filament\\Http\\Middleware\\Authenticate","Filament\\Http\\Middleware\\AuthenticateSession","Illuminate\\Foundation\\Http\\Middleware\\VerifyCsrfToken","Illuminate\\Routing\\Middleware\\SubstituteBindings","Filament\\Http\\Middleware\\DisableBladeIconComponents","Filament\\Http\\Middleware\\DispatchServingFilamentEvent"],"path":null},{"domain":null,"method":"GET|HEAD","uri":"admin\/users\/{record}","name":"filament.admin.resources.users.view","action":"App\\Filament\\Resources\\UserResource\\Pages\\ViewUser","middleware":["Filament\\Http\\Middleware\\SetUpPanel:admin","Illuminate\\Cookie\\Middleware\\EncryptCookies","Illuminate\\Cookie\\Middleware\\AddQueuedCookiesToResponse","Illuminate\\Session\\Middleware\\StartSession","Illuminate\\View\\Middleware\\ShareErrorsFromSession","Filament\\Http\\Middleware\\Authenticate","Filament\\Http\\Middleware\\AuthenticateSession","Illuminate\\Foundation\\Http\\Middleware\\VerifyCsrfToken","Illuminate\\Routing\\Middleware\\SubstituteBindings","Filament\\Http\\Middleware\\DisableBladeIconComponents","Filament\\Http\\Middleware\\DispatchServingFilamentEvent"],"path":null},{"domain":null,"method":"GET|HEAD","uri":"admin\/users\/{record}\/edit","name":"filament.admin.resources.users.edit","action":"App\\Filament\\Resources\\UserResource\\Pages\\EditUser","middleware":["Filament\\Http\\Middleware\\SetUpPanel:admin","Illuminate\\Cookie\\Middleware\\EncryptCookies","Illuminate\\Cookie\\Middleware\\AddQueuedCookiesToResponse","Illuminate\\Session\\Middleware\\StartSession","Illuminate\\View\\Middleware\\ShareErrorsFromSession","Filament\\Http\\Middleware\\Authenticate","Filament\\Http\\Middleware\\AuthenticateSession","Illuminate\\Foundation\\Http\\Middleware\\VerifyCsrfToken","Illuminate\\Routing\\Middleware\\SubstituteBindings","Filament\\Http\\Middleware\\DisableBladeIconComponents","Filament\\Http\\Middleware\\DispatchServingFilamentEvent"],"path":null},{"domain":null,"method":"POST","uri":"api\/v1\/admin\/impersonation\/end","name":"api.v1.admin.impersonation.end","action":"App\\Http\\Controllers\\Api\\V1\\Admin\\ImpersonationController@end","middleware":["api","Illuminate\\Auth\\Middleware\\Authenticate:sanctum"],"path":null},{"domain":null,"method":"POST","uri":"api\/v1\/admin\/impersonation\/start","name":"api.v1.admin.impersonation.start","action":"App\\Http\\Controllers\\Api\\V1\\Admin\\ImpersonationController@start","middleware":["api","Illuminate\\Auth\\Middleware\\Authenticate:sanctum"],"path":null},{"domain":null,"method":"POST","uri":"api\/v1\/attempts","name":"api.v1.attempts.store","action":"App\\Http\\Controllers\\Api\\V1\\Attempt\\AttemptController@store","middleware":["api","Illuminate\\Auth\\Middleware\\Authenticate:sanctum","Illuminate\\Routing\\Middleware\\ThrottleRequests:api"],"path":null},{"domain":null,"method":"POST","uri":"api\/v1\/attempts\/batch","name":"api.v1.attempts.batch","action":"App\\Http\\Controllers\\Api\\V1\\Attempt\\AttemptController@storeBatch","middleware":["api","Illuminate\\Auth\\Middleware\\Authenticate:sanctum","Illuminate\\Routing\\Middleware\\ThrottleRequests:api"],"path":null},{"domain":null,"method":"GET|HEAD","uri":"api\/v1\/auth\/email\/verify\/{id}\/{hash}","name":"api.v1.auth.verification.verify","action":"App\\Http\\Controllers\\Api\\V1\\Auth\\AuthController@verifyEmail","middleware":["api","Illuminate\\Routing\\Middleware\\ValidateSignature","Illuminate\\Routing\\Middleware\\ThrottleRequests:6,1"],"path":null},{"domain":null,"method":"POST","uri":"api\/v1\/auth\/login","name":"api.v1.auth.login","action":"App\\Http\\Controllers\\Api\\V1\\Auth\\AuthController@login","middleware":["api","Illuminate\\Routing\\Middleware\\ThrottleRequests:login"],"path":null},{"domain":null,"method":"POST","uri":"api\/v1\/auth\/logout","name":"api.v1.auth.logout","action":"App\\Http\\Controllers\\Api\\V1\\Auth\\AuthController@logout","middleware":["api","Illuminate\\Auth\\Middleware\\Authenticate:sanctum"],"path":null},{"domain":null,"method":"GET|HEAD","uri":"api\/v1\/auth\/me","name":"api.v1.auth.me","action":"App\\Http\\Controllers\\Api\\V1\\Auth\\AuthController@me","middleware":["api","Illuminate\\Auth\\Middleware\\Authenticate:sanctum"],"path":null},{"domain":null,"method":"POST","uri":"api\/v1\/auth\/password\/forgot","name":"api.v1.auth.password.forgot","action":"App\\Http\\Controllers\\Api\\V1\\Auth\\AuthController@forgotPassword","middleware":["api","Illuminate\\Routing\\Middleware\\ThrottleRequests:password-reset"],"path":null},{"domain":null,"method":"POST","uri":"api\/v1\/auth\/password\/reset","name":"api.v1.auth.password.reset","action":"App\\Http\\Controllers\\Api\\V1\\Auth\\AuthController@resetPassword","middleware":["api"],"path":null},{"domain":null,"method":"POST","uri":"api\/v1\/auth\/phone\/otp\/send","name":"api.v1.auth.phone.otp.send","action":"App\\Http\\Controllers\\Api\\V1\\Auth\\AuthController@sendOtp","middleware":["api","Illuminate\\Auth\\Middleware\\Authenticate:sanctum","Illuminate\\Routing\\Middleware\\ThrottleRequests:otp-send"],"path":null},{"domain":null,"method":"POST","uri":"api\/v1\/auth\/phone\/otp\/verify","name":"api.v1.auth.phone.otp.verify","action":"App\\Http\\Controllers\\Api\\V1\\Auth\\AuthController@verifyOtp","middleware":["api","Illuminate\\Auth\\Middleware\\Authenticate:sanctum","Illuminate\\Routing\\Middleware\\ThrottleRequests:otp-verify"],"path":null},{"domain":null,"method":"POST","uri":"api\/v1\/auth\/register","name":"api.v1.auth.register","action":"App\\Http\\Controllers\\Api\\V1\\Auth\\AuthController@register","middleware":["api","Illuminate\\Routing\\Middleware\\ThrottleRequests:register"],"path":null},{"domain":null,"method":"GET|HEAD","uri":"api\/v1\/exams","name":"api.v1.exams.index","action":"App\\Http\\Controllers\\Api\\V1\\Exam\\ExamController@index","middleware":["api"],"path":null},{"domain":null,"method":"GET|HEAD","uri":"api\/v1\/exams\/{code}\/subjects","name":"api.v1.exams.subjects","action":"App\\Http\\Controllers\\Api\\V1\\Exam\\ExamController@subjects","middleware":["api"],"path":null},{"domain":null,"method":"GET|HEAD","uri":"api\/v1\/exams\/{code}\/subjects\/{subjectId}","name":"api.v1.exams.topics","action":"App\\Http\\Controllers\\Api\\V1\\Exam\\ExamController@topics","middleware":["api"],"path":null},{"domain":null,"method":"POST","uri":"api\/v1\/family\/invite-new-student","name":"api.v1.family.invite","action":"App\\Http\\Controllers\\Api\\V1\\Family\\FamilyController@inviteNewStudent","middleware":["api","Illuminate\\Auth\\Middleware\\Authenticate:sanctum","Illuminate\\Routing\\Middleware\\ThrottleRequests:api"],"path":null},{"domain":null,"method":"POST","uri":"api\/v1\/family\/request-link","name":"api.v1.family.request-link","action":"App\\Http\\Controllers\\Api\\V1\\Family\\FamilyController@requestLink","middleware":["api","Illuminate\\Auth\\Middleware\\Authenticate:sanctum","Illuminate\\Routing\\Middleware\\ThrottleRequests:api"],"path":null},{"domain":null,"method":"GET|HEAD","uri":"api\/v1\/me\/context","name":"api.v1.me.context","action":"App\\Http\\Controllers\\Api\\V1\\Auth\\AuthController@context","middleware":["api","Illuminate\\Auth\\Middleware\\Authenticate:sanctum"],"path":null},{"domain":null,"method":"POST","uri":"api\/v1\/me\/data-export","name":"api.v1.me.data-export","action":"App\\Http\\Controllers\\Api\\V1\\Me\\ExportController","middleware":["api","Illuminate\\Auth\\Middleware\\Authenticate:sanctum"],"path":null},{"domain":null,"method":"POST","uri":"api\/v1\/me\/family\/claim-invite","name":"api.v1.me.family.claim","action":"App\\Http\\Controllers\\Api\\V1\\Family\\MeFamilyController@claimInvite","middleware":["api","Illuminate\\Auth\\Middleware\\Authenticate:sanctum","Illuminate\\Routing\\Middleware\\ThrottleRequests:api"],"path":null},{"domain":null,"method":"POST","uri":"api\/v1\/me\/family\/links\/{linkId}\/accept","name":"api.v1.me.family.accept","action":"App\\Http\\Controllers\\Api\\V1\\Family\\MeFamilyController@acceptLink","middleware":["api","Illuminate\\Auth\\Middleware\\Authenticate:sanctum","Illuminate\\Routing\\Middleware\\ThrottleRequests:api"],"path":null},{"domain":null,"method":"POST","uri":"api\/v1\/me\/family\/links\/{linkId}\/decline","name":"api.v1.me.family.decline","action":"App\\Http\\Controllers\\Api\\V1\\Family\\MeFamilyController@declineLink","middleware":["api","Illuminate\\Auth\\Middleware\\Authenticate:sanctum","Illuminate\\Routing\\Middleware\\ThrottleRequests:api"],"path":null},{"domain":null,"method":"PATCH","uri":"api\/v1\/me\/family\/links\/{linkId}\/permissions","name":"api.v1.me.family.permissions","action":"App\\Http\\Controllers\\Api\\V1\\Family\\MeFamilyController@updatePermissions","middleware":["api","Illuminate\\Auth\\Middleware\\Authenticate:sanctum","Illuminate\\Routing\\Middleware\\ThrottleRequests:api"],"path":null},{"domain":null,"method":"POST","uri":"api\/v1\/me\/family\/links\/{linkId}\/revoke","name":"api.v1.me.family.revoke","action":"App\\Http\\Controllers\\Api\\V1\\Family\\MeFamilyController@revokeLink","middleware":["api","Illuminate\\Auth\\Middleware\\Authenticate:sanctum","Illuminate\\Routing\\Middleware\\ThrottleRequests:api"],"path":null},{"domain":null,"method":"GET|HEAD","uri":"api\/v1\/me\/family\/pending","name":"api.v1.me.family.pending","action":"App\\Http\\Controllers\\Api\\V1\\Family\\MeFamilyController@pendingLinks","middleware":["api","Illuminate\\Auth\\Middleware\\Authenticate:sanctum","Illuminate\\Routing\\Middleware\\ThrottleRequests:api"],"path":null},{"domain":null,"method":"GET|HEAD","uri":"api\/v1\/me\/mastery","name":"api.v1.mastery.index","action":"App\\Http\\Controllers\\Api\\V1\\Mastery\\MasteryController@index","middleware":["api","Illuminate\\Auth\\Middleware\\Authenticate:sanctum","Illuminate\\Routing\\Middleware\\ThrottleRequests:api"],"path":null},{"domain":null,"method":"GET|HEAD","uri":"api\/v1\/me\/mastery\/topics\/{topic}","name":"api.v1.mastery.topic","action":"App\\Http\\Controllers\\Api\\V1\\Mastery\\MasteryController@topic","middleware":["api","Illuminate\\Auth\\Middleware\\Authenticate:sanctum","Illuminate\\Routing\\Middleware\\ThrottleRequests:api"],"path":null},{"domain":null,"method":"POST","uri":"api\/v1\/me\/mock-exams","name":"api.v1.mock-exams.store","action":"App\\Http\\Controllers\\Api\\V1\\MockExam\\MockExamController@store","middleware":["api","Illuminate\\Auth\\Middleware\\Authenticate:sanctum","Illuminate\\Routing\\Middleware\\ThrottleRequests:api"],"path":null},{"domain":null,"method":"GET|HEAD","uri":"api\/v1\/me\/mock-exams\/{mockExam}\/next","name":"api.v1.mock-exams.next","action":"App\\Http\\Controllers\\Api\\V1\\MockExam\\MockExamController@next","middleware":["api","Illuminate\\Auth\\Middleware\\Authenticate:sanctum","Illuminate\\Routing\\Middleware\\ThrottleRequests:api"],"path":null},{"domain":null,"method":"POST","uri":"api\/v1\/me\/mock-exams\/{mockExam}\/submit","name":"api.v1.mock-exams.submit","action":"App\\Http\\Controllers\\Api\\V1\\MockExam\\MockExamController@submit","middleware":["api","Illuminate\\Auth\\Middleware\\Authenticate:sanctum","Illuminate\\Routing\\Middleware\\ThrottleRequests:api"],"path":null},{"domain":null,"method":"GET|HEAD","uri":"api\/v1\/me\/sessions","name":"api.v1.sessions.index","action":"App\\Http\\Controllers\\Api\\V1\\Session\\StudySessionController@index","middleware":["api","Illuminate\\Auth\\Middleware\\Authenticate:sanctum","Illuminate\\Routing\\Middleware\\ThrottleRequests:api"],"path":null},{"domain":null,"method":"POST","uri":"api\/v1\/me\/sessions","name":"api.v1.sessions.store","action":"App\\Http\\Controllers\\Api\\V1\\Session\\StudySessionController@store","middleware":["api","Illuminate\\Auth\\Middleware\\Authenticate:sanctum","Illuminate\\Routing\\Middleware\\ThrottleRequests:api"],"path":null},{"domain":null,"method":"POST","uri":"api\/v1\/me\/sessions\/{studySession}\/end","name":"api.v1.sessions.end","action":"App\\Http\\Controllers\\Api\\V1\\Session\\StudySessionController@end","middleware":["api","Illuminate\\Auth\\Middleware\\Authenticate:sanctum","Illuminate\\Routing\\Middleware\\ThrottleRequests:api"],"path":null},{"domain":null,"method":"GET|HEAD","uri":"api\/v1\/me\/study-plan","name":"api.v1.me.study-plan","action":"App\\Http\\Controllers\\Api\\V1\\AI\\StudyPlanController@current","middleware":["api","Illuminate\\Auth\\Middleware\\Authenticate:sanctum","Illuminate\\Routing\\Middleware\\ThrottleRequests:api"],"path":null},{"domain":null,"method":"POST","uri":"api\/v1\/me\/study-plan\/regenerate","name":"api.v1.me.study-plan.regenerate","action":"App\\Http\\Controllers\\Api\\V1\\AI\\StudyPlanController@regenerate","middleware":["api","Illuminate\\Auth\\Middleware\\Authenticate:sanctum","Illuminate\\Routing\\Middleware\\ThrottleRequests:api","Illuminate\\Routing\\Middleware\\ThrottleRequests:ai-study-plan"],"path":null},{"domain":null,"method":"GET|HEAD","uri":"api\/v1\/me\/subscription","name":"api.v1.me.subscription.current","action":"App\\Http\\Controllers\\Api\\V1\\Billing\\SubscriptionController@current","middleware":["api","Illuminate\\Auth\\Middleware\\Authenticate:sanctum","Illuminate\\Routing\\Middleware\\ThrottleRequests:api"],"path":null},{"domain":null,"method":"POST","uri":"api\/v1\/me\/subscription\/start","name":"api.v1.me.subscription.start","action":"App\\Http\\Controllers\\Api\\V1\\Billing\\SubscriptionController@start","middleware":["api","Illuminate\\Auth\\Middleware\\Authenticate:sanctum","Illuminate\\Routing\\Middleware\\ThrottleRequests:api"],"path":null},{"domain":null,"method":"POST","uri":"api\/v1\/me\/subscription\/{subscriptionId}\/cancel","name":"api.v1.me.subscription.cancel","action":"App\\Http\\Controllers\\Api\\V1\\Billing\\SubscriptionController@cancel","middleware":["api","Illuminate\\Auth\\Middleware\\Authenticate:sanctum","Illuminate\\Routing\\Middleware\\ThrottleRequests:api"],"path":null},{"domain":null,"method":"POST","uri":"api\/v1\/me\/tutor\/sessions","name":"api.v1.me.tutor.start","action":"App\\Http\\Controllers\\Api\\V1\\AI\\TutorController@startSession","middleware":["api","Illuminate\\Auth\\Middleware\\Authenticate:sanctum","Illuminate\\Routing\\Middleware\\ThrottleRequests:api"],"path":null},{"domain":null,"method":"GET|HEAD","uri":"api\/v1\/me\/tutor\/sessions","name":"api.v1.me.tutor.list","action":"App\\Http\\Controllers\\Api\\V1\\AI\\TutorController@listSessions","middleware":["api","Illuminate\\Auth\\Middleware\\Authenticate:sanctum","Illuminate\\Routing\\Middleware\\ThrottleRequests:api"],"path":null},{"domain":null,"method":"GET|HEAD","uri":"api\/v1\/me\/tutor\/sessions\/{sessionId}\/messages","name":"api.v1.me.tutor.messages","action":"App\\Http\\Controllers\\Api\\V1\\AI\\TutorController@messages","middleware":["api","Illuminate\\Auth\\Middleware\\Authenticate:sanctum","Illuminate\\Routing\\Middleware\\ThrottleRequests:api"],"path":null},{"domain":null,"method":"POST","uri":"api\/v1\/me\/tutor\/sessions\/{sessionId}\/messages","name":"api.v1.me.tutor.send","action":"App\\Http\\Controllers\\Api\\V1\\AI\\TutorController@sendMessage","middleware":["api","Illuminate\\Auth\\Middleware\\Authenticate:sanctum","Illuminate\\Routing\\Middleware\\ThrottleRequests:api","Illuminate\\Routing\\Middleware\\ThrottleRequests:ai-tutor"],"path":null},{"domain":null,"method":"POST","uri":"api\/v1\/onboarding\/complete","name":"api.v1.onboarding.complete","action":"App\\Http\\Controllers\\Api\\V1\\Onboarding\\OnboardingController@complete","middleware":["api","Illuminate\\Auth\\Middleware\\Authenticate:sanctum"],"path":null},{"domain":null,"method":"POST","uri":"api\/v1\/onboarding\/exam-targets","name":"api.v1.onboarding.exam-targets","action":"App\\Http\\Controllers\\Api\\V1\\Onboarding\\OnboardingController@setExamTargets","middleware":["api","Illuminate\\Auth\\Middleware\\Authenticate:sanctum"],"path":null},{"domain":null,"method":"POST","uri":"api\/v1\/onboarding\/subjects","name":"api.v1.onboarding.subjects","action":"App\\Http\\Controllers\\Api\\V1\\Onboarding\\OnboardingController@setSubjects","middleware":["api","Illuminate\\Auth\\Middleware\\Authenticate:sanctum"],"path":null},{"domain":null,"method":"GET|HEAD","uri":"api\/v1\/parent\/children","name":"api.v1.parent.children.index","action":"App\\Http\\Controllers\\Api\\V1\\Family\\FamilyController@children","middleware":["api","Illuminate\\Auth\\Middleware\\Authenticate:sanctum","Illuminate\\Routing\\Middleware\\ThrottleRequests:api"],"path":null},{"domain":null,"method":"GET|HEAD","uri":"api\/v1\/parent\/children\/{studentId}","name":"api.v1.parent.children.show","action":"App\\Http\\Controllers\\Api\\V1\\Family\\FamilyController@childSummary","middleware":["api","Illuminate\\Auth\\Middleware\\Authenticate:sanctum","Illuminate\\Routing\\Middleware\\ThrottleRequests:api"],"path":null},{"domain":null,"method":"POST","uri":"api\/v1\/parent\/children\/{studentId}\/encouragement","name":"api.v1.parent.children.encouragement","action":"App\\Http\\Controllers\\Api\\V1\\Family\\FamilyController@sendEncouragement","middleware":["api","Illuminate\\Auth\\Middleware\\Authenticate:sanctum","Illuminate\\Routing\\Middleware\\ThrottleRequests:api"],"path":null},{"domain":null,"method":"POST","uri":"api\/v1\/parent\/children\/{studentId}\/subscription\/start","name":"api.v1.parent.children.subscription.start","action":"App\\Http\\Controllers\\Api\\V1\\Billing\\SubscriptionController@startForStudent","middleware":["api","Illuminate\\Auth\\Middleware\\Authenticate:sanctum","Illuminate\\Routing\\Middleware\\ThrottleRequests:api"],"path":null},{"domain":null,"method":"GET|HEAD","uri":"api\/v1\/plans","name":"api.v1.plans.index","action":"App\\Http\\Controllers\\Api\\V1\\Billing\\PlansController@index","middleware":["api"],"path":null},{"domain":null,"method":"GET|HEAD","uri":"api\/v1\/questions","name":"api.v1.questions.index","action":"App\\Http\\Controllers\\Api\\V1\\Question\\QuestionController@index","middleware":["api","Illuminate\\Auth\\Middleware\\Authenticate:sanctum","Illuminate\\Routing\\Middleware\\ThrottleRequests:api"],"path":null},{"domain":null,"method":"GET|HEAD","uri":"api\/v1\/questions\/{questionId}\/explanation","name":"api.v1.questions.explanation","action":"App\\Http\\Controllers\\Api\\V1\\AI\\ExplanationController","middleware":["api","Illuminate\\Auth\\Middleware\\Authenticate:sanctum","Illuminate\\Routing\\Middleware\\ThrottleRequests:api","Illuminate\\Routing\\Middleware\\ThrottleRequests:ai-explanation"],"path":null},{"domain":null,"method":"GET|HEAD","uri":"api\/v1\/questions\/{question}","name":"api.v1.questions.show","action":"App\\Http\\Controllers\\Api\\V1\\Question\\QuestionController@show","middleware":["api","Illuminate\\Auth\\Middleware\\Authenticate:sanctum","Illuminate\\Routing\\Middleware\\ThrottleRequests:api"],"path":null},{"domain":null,"method":"POST","uri":"api\/v1\/questions\/{question}\/report","name":"api.v1.questions.report","action":"App\\Http\\Controllers\\Api\\V1\\Question\\QuestionController@report","middleware":["api","Illuminate\\Auth\\Middleware\\Authenticate:sanctum","Illuminate\\Routing\\Middleware\\ThrottleRequests:api"],"path":null},{"domain":null,"method":"GET|HEAD","uri":"api\/v1\/questions\/{question}\/similar","name":"api.v1.questions.similar","action":"App\\Http\\Controllers\\Api\\V1\\Question\\QuestionController@similar","middleware":["api","Illuminate\\Auth\\Middleware\\Authenticate:sanctum","Illuminate\\Routing\\Middleware\\ThrottleRequests:api"],"path":null},{"domain":null,"method":"POST","uri":"api\/v1\/webhooks\/paystack","name":"api.v1.webhooks.paystack","action":"App\\Http\\Controllers\\Api\\V1\\Billing\\WebhookController@paystack","middleware":["api"],"path":null},{"domain":null,"method":"GET|HEAD","uri":"filament\/exports\/{export}\/download","name":"filament.exports.download","action":"Filament\\Actions\\Exports\\Http\\Controllers\\DownloadExport","middleware":["filament.actions"],"path":null},{"domain":null,"method":"GET|HEAD","uri":"filament\/imports\/{import}\/failed-rows\/download","name":"filament.imports.failed-rows.download","action":"Filament\\Actions\\Imports\\Http\\Controllers\\DownloadImportFailureCsv","middleware":["filament.actions"],"path":null},{"domain":null,"method":"GET|HEAD","uri":"livewire\/livewire.js","name":null,"action":"Livewire\\Mechanisms\\FrontendAssets\\FrontendAssets@returnJavaScriptAsFile","middleware":[],"path":null},{"domain":null,"method":"GET|HEAD","uri":"livewire\/livewire.min.js.map","name":null,"action":"Livewire\\Mechanisms\\FrontendAssets\\FrontendAssets@maps","middleware":[],"path":null},{"domain":null,"method":"GET|HEAD","uri":"livewire\/preview-file\/{filename}","name":"livewire.preview-file","action":"Livewire\\Features\\SupportFileUploads\\FilePreviewController@handle","middleware":["web"],"path":null},{"domain":null,"method":"POST","uri":"livewire\/update","name":"default.livewire.update","action":"Livewire\\Mechanisms\\HandleRequests\\HandleRequests@handleUpdate","middleware":["web"],"path":null},{"domain":null,"method":"POST","uri":"livewire\/upload-file","name":"livewire.upload-file","action":"Livewire\\Features\\SupportFileUploads\\FileUploadController@handle","middleware":["web","Illuminate\\Routing\\Middleware\\ThrottleRequests:60,1"],"path":null},{"domain":null,"method":"GET|HEAD","uri":"sanctum\/csrf-cookie","name":"sanctum.csrf-cookie","action":"Laravel\\Sanctum\\Http\\Controllers\\CsrfCookieController@show","middleware":["web"],"path":null},{"domain":null,"method":"GET|HEAD","uri":"up","name":null,"action":"Closure","middleware":[],"path":"vendor\/laravel\/framework\/src\/Illuminate\/Foundation\/Configuration\/ApplicationBuilder.php:219"}]
